.testr.conf
AUTHORS
ChangeLog
LICENSE
README.rst
requirements.txt
setup.cfg
setup.py
test-requirements.txt
tox.ini
dallasMQTT/__init__.py
dallasMQTT/listener.py
dallasMQTT.egg-info/PKG-INFO
dallasMQTT.egg-info/SOURCES.txt
dallasMQTT.egg-info/dependency_links.txt
dallasMQTT.egg-info/entry_points.txt
dallasMQTT.egg-info/not-zip-safe
dallasMQTT.egg-info/pbr.json
dallasMQTT.egg-info/requires.txt
dallasMQTT.egg-info/top_level.txt
dallasMQTT/tests/__init__.py
dallasMQTT/tests/base.py
dallasMQTT/tests/test_dallas_mqtt.py
doc/source/conf.py
doc/source/index.rst
doc/source/readme.rst